skymith-0.0.1.dist-info/METADATA
skymith-0.0.1.dist-info/WHEEL
skymith-0.0.1.dist-info/entry_points.txt
skymith/sdk/__init__.py
skymith/sdk/buffet/__init__.py
skymith/sdk/buffet/langchain_tool.py
skymith/sdk/constants.py
skymith/sdk/endpoints.py
skymith/sdk/holmes/__init__.py
skymith/sdk/holmes/langchain_tool.py
skymith/sdk/models.py
skymith/sdk/strider/__init__.py
skymith/sdk/strider/langchain_tool.py
skymith-0.0.1.dist-info/RECORD
