Metadata-Version: 2.1
Name: skymith
Version: 0.0.1
Summary: Flexible AI-driven services, everywhere, and for everyone.
Author-Email: Mitheithel Team <hello@mitheithel.com>
License: MIT
Classifier: Programming Language :: Python :: 3
Classifier: License :: OSI Approved :: MIT License
Classifier: Operating System :: OS Independent
Project-URL: Homepage, https://skymith.com
Project-URL: GitHub, https://github.com/Mitheithel/skymith
Project-URL: Documentation, https://docs.skymith.com/skymith
Project-URL: Bug Tracker, https://github.com/Mitheithel/skymith/issues
Requires-Python: <3.12,>=3.10
Requires-Dist: httpx>=0.28.1
Requires-Dist: websockets>=15.0
Requires-Dist: langchain>=0.3.18
Provides-Extra: testing
Requires-Dist: pytest; extra == "testing"
Requires-Dist: pytest-cov; extra == "testing"
Requires-Dist: pytest-asyncio>=0.25.3; extra == "testing"
